LICENSE
README.md
pyproject.toml
setup.py
wandb_addons/__init__.py
wandb_addons.egg-info/PKG-INFO
wandb_addons.egg-info/SOURCES.txt
wandb_addons.egg-info/dependency_links.txt
wandb_addons.egg-info/entry_points.txt
wandb_addons.egg-info/requires.txt
wandb_addons.egg-info/top_level.txt
wandb_addons/cli/__init__.py
wandb_addons/cli/cli.py
wandb_addons/storage/__init__.py
wandb_addons/storage/cleaner.py